bigtests/__init__.py
screed/DBConstants.py
screed/__init__.py
screed/__main__.py
screed/conversion.py
screed/createscreed.py
screed/dna.py
screed/dump_fasta.py
screed/dump_fastq.py
screed/fasta.py
screed/fastq.py
screed/hava.py
screed/openscreed.py
screed/pygr_api.py
screed/screedRecord.py
screed/seqparse.py
screed/utils.py
screed/version.py
screed/tests/__init__.py
screed/tests/havaGen.py
screed/tests/screed_tst_utils.py
screed/tests/test_attriberror.py
screed/tests/test_convert.py
screed/tests/test_db.py
screed/tests/test_dictionary.py
screed/tests/test_dna.py
screed/tests/test_fasta.py
screed/tests/test_fasta_recover.py
screed/tests/test_fastq.py
screed/tests/test_fastq_recover.py
screed/tests/test_hava_methods.py
screed/tests/test_open.py
screed/tests/test_open_cm.py
screed/tests/test_pygr_api.py
screed/tests/test_record.py
screed/tests/test_shell.py
screed/tests/test_streaming.py
screed/tests/test-data/empty.fa
screed/tests/test-data/test-whitespace.fa
screed/tests/test-data/test.fa
screed/tests/test-data/test.fa.bz2
screed/tests/test-data/test.fa.gz
screed/tests/test-data/test.fa.zip
screed/tests/test-data/test.fastq
screed/tests/test-data/test.fastq.bz2
screed/tests/test-data/test.fastq.gz
screed/tests/test-data/test.hava
screed-1.1.2.dist-info/LICENSE.rst
screed-1.1.2.dist-info/METADATA
screed-1.1.2.dist-info/WHEEL
screed-1.1.2.dist-info/entry_points.txt
screed-1.1.2.dist-info/top_level.txt
screed-1.1.2.dist-info/RECORD
