Metadata-Version: 2.1
Name: screed
Version: 1.1.2
Summary: a Python library for loading FASTA and FASTQ sequences
Home-page: https://github.com/dib-lab/screed
Author: Alex Nolley, C. Titus Brown
Author-email: ctbrown@ucdavis.edu,
License: BSD 3-clause
Project-URL: Documentation, https://screed.readthedocs.io
Project-URL: Source, https://github.com/dib-lab/screed
Project-URL: Tracker, https://github.com/dib-lab/screed/issues
Classifier: Development Status :: 5 - Production/Stable
Classifier: Environment :: Console
Classifier: Environment :: MacOS X
Classifier: Intended Audience :: Science/Research
Classifier: License :: OSI Approved :: BSD License
Classifier: Natural Language :: English
Classifier: Operating System :: POSIX :: Linux
Classifier: Operating System :: MacOS :: MacOS X
Classifier: Programming Language :: Python :: 3.7
Classifier: Programming Language :: Python :: 3.8
Classifier: Programming Language :: Python :: 3.9
Classifier: Topic :: Scientific/Engineering :: Bio-Informatics
Requires-Python: >=3.7
Provides-Extra: test
Provides-Extra: all
License-File: doc/LICENSE.rst
